{
    "sourceFile": "src/components/header/SideBar.js",
    "activeCommit": 0,
    "commits": [
        {
            "activePatchIndex": 45,
            "patches": [
                {
                    "date": 1641554524665,
                    "content": "Index: \n===================================================================\n--- \n+++ \n"
                },
                {
                    "date": 1641555116118,
                    "content": "Index: \n===================================================================\n--- \n+++ \n@@ -0,0 +1,11 @@\n+import React from \"react\";\n+\n+const SideBar = (props) => {\n+  return (\n+    <div>\n+      <div>zz</div>\n+    </div>\n+  );\n+};\n+\n+export default SideBar;\n"
                },
                {
                    "date": 1641555202590,
                    "content": "Index: \n===================================================================\n--- \n+++ \n@@ -2,9 +2,9 @@\n \n const SideBar = (props) => {\n   return (\n     <div>\n-      <div>zz</div>\n+      <div>SideBar</div>\n     </div>\n   );\n };\n \n"
                },
                {
                    "date": 1641555269613,
                    "content": "Index: \n===================================================================\n--- \n+++ \n@@ -2,9 +2,54 @@\n \n const SideBar = (props) => {\n   return (\n     <div>\n-      <div>SideBar</div>\n+      <div class=\"logo-details\">\n+\t  <button type=\"button\" class=\"btn-side-open\"><img src=\"../resource/images/common/ico_logo-mark.png\" alt=\"오더체크\"></button>\n+\t  <h1 class=\"logo_name\"><img src=\"../resource/images/common/ico_logo-name.png\" alt=\"오더체크\"/></h1>\n+\t</div>\n+\t\n+\t<ul class=\"nav-list\">\n+\t  <li>\n+\t    <a href=\"dashboard.html\">\n+\t      <i class='ico home'></i>\n+\t      <span class=\"links_name\">홈</span>\n+\t    </a>\n+\t  </li>\n+\t  <li class=\"on\">\n+\t    <a href=\"customManage_list.html\">\n+\t      <i class=\"ico user\"></i>\n+\t      <span class=\"links_name\">고객 관리</span>\n+\t    </a>\n+\t  </li>\n+\t  <li>\n+\t    <a href=\"file_storage.html\">\n+\t      <i class='ico file'></i>\n+\t      <span class=\"links_name\">파일 보관함</span>\n+\t    </a>\n+\t  </li>\n+\t  <li>\n+\t    <a href=\"form_list.html\">\n+\t      <i class='ico form'></i>\n+\t      <span class=\"links_name\">상담 신청폼</span>\n+\t    </a>\n+\t  </li>\n+\t</ul>\n+  <ul class=\"btm\">\n+    <li>\n+      <a href=\"#\">\n+        <i class='ico help'></i>\n+        <span class=\"links_name\">자주 묻는 질문</span>\n+      </a>\n+    </li>\n+    <li>\n+      <a href=\"setting_company-info.html\">\n+        <i class='ico setting'></i>\n+        <span class=\"links_name\">설정</span>\n+      </a>\n+    </li>\n+  </ul>\n+  <button type=\"button\" class=\"btn-lnb-close\"><span class=\"hide\">메뉴 닫기</span></button>\n     </div>\n   );\n };\n \n"
                },
                {
                    "date": 1641555315578,
                    "content": "Index: \n===================================================================\n--- \n+++ \n@@ -3,53 +3,63 @@\n const SideBar = (props) => {\n   return (\n     <div>\n       <div class=\"logo-details\">\n-\t  <button type=\"button\" class=\"btn-side-open\"><img src=\"../resource/images/common/ico_logo-mark.png\" alt=\"오더체크\"></button>\n-\t  <h1 class=\"logo_name\"><img src=\"../resource/images/common/ico_logo-name.png\" alt=\"오더체크\"/></h1>\n-\t</div>\n-\t\n-\t<ul class=\"nav-list\">\n-\t  <li>\n-\t    <a href=\"dashboard.html\">\n-\t      <i class='ico home'></i>\n-\t      <span class=\"links_name\">홈</span>\n-\t    </a>\n-\t  </li>\n-\t  <li class=\"on\">\n-\t    <a href=\"customManage_list.html\">\n-\t      <i class=\"ico user\"></i>\n-\t      <span class=\"links_name\">고객 관리</span>\n-\t    </a>\n-\t  </li>\n-\t  <li>\n-\t    <a href=\"file_storage.html\">\n-\t      <i class='ico file'></i>\n-\t      <span class=\"links_name\">파일 보관함</span>\n-\t    </a>\n-\t  </li>\n-\t  <li>\n-\t    <a href=\"form_list.html\">\n-\t      <i class='ico form'></i>\n-\t      <span class=\"links_name\">상담 신청폼</span>\n-\t    </a>\n-\t  </li>\n-\t</ul>\n-  <ul class=\"btm\">\n-    <li>\n-      <a href=\"#\">\n-        <i class='ico help'></i>\n-        <span class=\"links_name\">자주 묻는 질문</span>\n-      </a>\n-    </li>\n-    <li>\n-      <a href=\"setting_company-info.html\">\n-        <i class='ico setting'></i>\n-        <span class=\"links_name\">설정</span>\n-      </a>\n-    </li>\n-  </ul>\n-  <button type=\"button\" class=\"btn-lnb-close\"><span class=\"hide\">메뉴 닫기</span></button>\n+        {/* <button type=\"button\" class=\"btn-side-open\"><img src=\"../resource/images/common/ico_logo-mark.png\" alt=\"오더체크\"></button> */}\n+        <button type=\"button\" class=\"btn-side-open\">\n+          zz\n+        </button>\n+        <h1 class=\"logo_name\">\n+          <img\n+            src=\"../resource/images/common/ico_logo-name.png\"\n+            alt=\"오더체크\"\n+          />\n+        </h1>\n+      </div>\n+\n+      <ul class=\"nav-list\">\n+        <li>\n+          <a href=\"dashboard.html\">\n+            <i class=\"ico home\"></i>\n+            <span class=\"links_name\">홈</span>\n+          </a>\n+        </li>\n+        <li class=\"on\">\n+          <a href=\"customManage_list.html\">\n+            <i class=\"ico user\"></i>\n+            <span class=\"links_name\">고객 관리</span>\n+          </a>\n+        </li>\n+        <li>\n+          <a href=\"file_storage.html\">\n+            <i class=\"ico file\"></i>\n+            <span class=\"links_name\">파일 보관함</span>\n+          </a>\n+        </li>\n+        <li>\n+          <a href=\"form_list.html\">\n+            <i class=\"ico form\"></i>\n+            <span class=\"links_name\">상담 신청폼</span>\n+          </a>\n+        </li>\n+      </ul>\n+      <ul class=\"btm\">\n+        <li>\n+          <a href=\"#\">\n+            <i class=\"ico help\"></i>\n+            <span class=\"links_name\">자주 묻는 질문</span>\n+          </a>\n+        </li>\n+        <li>\n+          <a href=\"setting_company-info.html\">\n+            <i class=\"ico setting\"></i>\n+            <span class=\"links_name\">설정</span>\n+          </a>\n+        </li>\n+      </ul>\n+      <button type=\"button\" class=\"btn-lnb-close\">\n+        <span class=\"hide\">메뉴 닫기</span>\n+      </button>\n     </div>\n   );\n };\n \n"
                },
                {
                    "date": 1641555488782,
                    "content": "Index: \n===================================================================\n--- \n+++ \n@@ -1,5 +1,6 @@\n import React from \"react\";\n+import SideBar.css from '../../style/css/layout.css'\n \n const SideBar = (props) => {\n   return (\n     <div>\n"
                },
                {
                    "date": 1641555533304,
                    "content": "Index: \n===================================================================\n--- \n+++ \n@@ -1,10 +1,10 @@\n import React from \"react\";\n-import SideBar.css from '../../style/css/layout.css'\n+import \"../../style/css/layout.css\";\n \n const SideBar = (props) => {\n   return (\n-    <div>\n+    <div class=\"sidebar\">\n       <div class=\"logo-details\">\n         {/* <button type=\"button\" class=\"btn-side-open\"><img src=\"../resource/images/common/ico_logo-mark.png\" alt=\"오더체크\"></button> */}\n         <button type=\"button\" class=\"btn-side-open\">\n           zz\n"
                },
                {
                    "date": 1641555606812,
                    "content": "Index: \n===================================================================\n--- \n+++ \n@@ -2,64 +2,64 @@\n import \"../../style/css/layout.css\";\n \n const SideBar = (props) => {\n   return (\n-    <div class=\"sidebar\">\n-      <div class=\"logo-details\">\n-        {/* <button type=\"button\" class=\"btn-side-open\"><img src=\"../resource/images/common/ico_logo-mark.png\" alt=\"오더체크\"></button> */}\n-        <button type=\"button\" class=\"btn-side-open\">\n+    <div className=\"sidebar\">\n+      <div className=\"logo-details\">\n+        {/* <button type=\"button\" className=\"btn-side-open\"><img src=\"../resource/images/common/ico_logo-mark.png\" alt=\"오더체크\"></button> */}\n+        <button type=\"button\" className=\"btn-side-open\">\n           zz\n         </button>\n-        <h1 class=\"logo_name\">\n+        <h1 className=\"logo_name\">\n           <img\n             src=\"../resource/images/common/ico_logo-name.png\"\n             alt=\"오더체크\"\n           />\n         </h1>\n       </div>\n \n-      <ul class=\"nav-list\">\n+      <ul className=\"nav-list\">\n         <li>\n           <a href=\"dashboard.html\">\n-            <i class=\"ico home\"></i>\n-            <span class=\"links_name\">홈</span>\n+            <i className=\"ico home\"></i>\n+            <span className=\"links_name\">홈</span>\n           </a>\n         </li>\n-        <li class=\"on\">\n+        <li className=\"on\">\n           <a href=\"customManage_list.html\">\n-            <i class=\"ico user\"></i>\n-            <span class=\"links_name\">고객 관리</span>\n+            <i className=\"ico user\"></i>\n+            <span className=\"links_name\">고객 관리</span>\n           </a>\n         </li>\n         <li>\n           <a href=\"file_storage.html\">\n-            <i class=\"ico file\"></i>\n-            <span class=\"links_name\">파일 보관함</span>\n+            <i className=\"ico file\"></i>\n+            <span className=\"links_name\">파일 보관함</span>\n           </a>\n         </li>\n         <li>\n           <a href=\"form_list.html\">\n-            <i class=\"ico form\"></i>\n-            <span class=\"links_name\">상담 신청폼</span>\n+            <i className=\"ico form\"></i>\n+            <span className=\"links_name\">상담 신청폼</span>\n           </a>\n         </li>\n       </ul>\n-      <ul class=\"btm\">\n+      <ul className=\"btm\">\n         <li>\n           <a href=\"#\">\n-            <i class=\"ico help\"></i>\n-            <span class=\"links_name\">자주 묻는 질문</span>\n+            <i className=\"ico help\"></i>\n+            <span className=\"links_name\">자주 묻는 질문</span>\n           </a>\n         </li>\n         <li>\n           <a href=\"setting_company-info.html\">\n-            <i class=\"ico setting\"></i>\n-            <span class=\"links_name\">설정</span>\n+            <i className=\"ico setting\"></i>\n+            <span className=\"links_name\">설정</span>\n           </a>\n         </li>\n       </ul>\n-      <button type=\"button\" class=\"btn-lnb-close\">\n-        <span class=\"hide\">메뉴 닫기</span>\n+      <button type=\"button\" className=\"btn-lnb-close\">\n+        <span className=\"hide\">메뉴 닫기</span>\n       </button>\n     </div>\n   );\n };\n"
                },
                {
                    "date": 1641555819962,
                    "content": "Index: \n===================================================================\n--- \n+++ \n@@ -10,9 +10,9 @@\n           zz\n         </button>\n         <h1 className=\"logo_name\">\n           <img\n-            src=\"../resource/images/common/ico_logo-name.png\"\n+            src=\"../../resource/images/common/ico_logo-name.png\"\n             alt=\"오더체크\"\n           />\n         </h1>\n       </div>\n"
                },
                {
                    "date": 1641555838529,
                    "content": "Index: \n===================================================================\n--- \n+++ \n@@ -4,10 +4,9 @@\n const SideBar = (props) => {\n   return (\n     <div className=\"sidebar\">\n       <div className=\"logo-details\">\n-        {/* <button type=\"button\" className=\"btn-side-open\"><img src=\"../resource/images/common/ico_logo-mark.png\" alt=\"오더체크\"></button> */}\n-        <button type=\"button\" className=\"btn-side-open\">\n+        <button type=\"button\" className=\"btn-side-open\"><img src=\"../../resource/images/common/ico_logo-mark.png\" alt=\"오더체크\"></button>\n           zz\n         </button>\n         <h1 className=\"logo_name\">\n           <img\n"
                },
                {
                    "date": 1641555869749,
                    "content": "Index: \n===================================================================\n--- \n+++ \n@@ -2,8 +2,9 @@\n import \"../../style/css/layout.css\";\n \n const SideBar = (props) => {\n   return (\n+    <>\n     <div className=\"sidebar\">\n       <div className=\"logo-details\">\n         <button type=\"button\" className=\"btn-side-open\"><img src=\"../../resource/images/common/ico_logo-mark.png\" alt=\"오더체크\"></button>\n           zz\n@@ -59,8 +60,9 @@\n       <button type=\"button\" className=\"btn-lnb-close\">\n         <span className=\"hide\">메뉴 닫기</span>\n       </button>\n     </div>\n+    </>\n   );\n };\n \n export default SideBar;\n"
                },
                {
                    "date": 1641555878596,
                    "content": "Index: \n===================================================================\n--- \n+++ \n@@ -2,9 +2,8 @@\n import \"../../style/css/layout.css\";\n \n const SideBar = (props) => {\n   return (\n-    <>\n     <div className=\"sidebar\">\n       <div className=\"logo-details\">\n         <button type=\"button\" className=\"btn-side-open\"><img src=\"../../resource/images/common/ico_logo-mark.png\" alt=\"오더체크\"></button>\n           zz\n@@ -60,9 +59,8 @@\n       <button type=\"button\" className=\"btn-lnb-close\">\n         <span className=\"hide\">메뉴 닫기</span>\n       </button>\n     </div>\n-    </>\n   );\n };\n \n export default SideBar;\n"
                },
                {
                    "date": 1641555889050,
                    "content": "Index: \n===================================================================\n--- \n+++ \n@@ -58,9 +58,10 @@\n       </ul>\n       <button type=\"button\" className=\"btn-lnb-close\">\n         <span className=\"hide\">메뉴 닫기</span>\n       </button>\n-    </div>\n+    </div >\n+      </div>\n   );\n };\n \n export default SideBar;\n"
                },
                {
                    "date": 1641555928413,
                    "content": "Index: \n===================================================================\n--- \n+++ \n@@ -58,10 +58,9 @@\n       </ul>\n       <button type=\"button\" className=\"btn-lnb-close\">\n         <span className=\"hide\">메뉴 닫기</span>\n       </button>\n-    </div >\n-      </div>\n+  </div >\n   );\n };\n \n export default SideBar;\n"
                },
                {
                    "date": 1641555935601,
                    "content": "Index: \n===================================================================\n--- \n+++ \n@@ -58,9 +58,9 @@\n       </ul>\n       <button type=\"button\" className=\"btn-lnb-close\">\n         <span className=\"hide\">메뉴 닫기</span>\n       </button>\n-  </div >\n+    </div >\n   );\n };\n \n export default SideBar;\n"
                },
                {
                    "date": 1641555985449,
                    "content": "Index: \n===================================================================\n--- \n+++ \n@@ -2,65 +2,56 @@\n import \"../../style/css/layout.css\";\n \n const SideBar = (props) => {\n   return (\n-    <div className=\"sidebar\">\n-      <div className=\"logo-details\">\n-        <button type=\"button\" className=\"btn-side-open\"><img src=\"../../resource/images/common/ico_logo-mark.png\" alt=\"오더체크\"></button>\n-          zz\n-        </button>\n-        <h1 className=\"logo_name\">\n-          <img\n-            src=\"../../resource/images/common/ico_logo-name.png\"\n-            alt=\"오더체크\"\n-          />\n-        </h1>\n+    <nav class=\"sidebar\">\n+      <div class=\"logo-details\">\n+        <button type=\"button\" class=\"btn-side-open\"><img src=\"../resource/images/common/ico_logo-mark.png\" alt=\"오더체크\"></button>\n+        <h1 class=\"logo_name\"><img src=\"../resource/images/common/ico_logo-name.png\" alt=\"오더체크\"/></h1>\n       </div>\n \n-      <ul className=\"nav-list\">\n+      <ul class=\"nav-list\">\n         <li>\n           <a href=\"dashboard.html\">\n-            <i className=\"ico home\"></i>\n-            <span className=\"links_name\">홈</span>\n+            <i class='ico home'></i>\n+            <span class=\"links_name\">홈</span>\n           </a>\n         </li>\n-        <li className=\"on\">\n+        <li class=\"on\">\n           <a href=\"customManage_list.html\">\n-            <i className=\"ico user\"></i>\n-            <span className=\"links_name\">고객 관리</span>\n+            <i class=\"ico user\"></i>\n+            <span class=\"links_name\">고객 관리</span>\n           </a>\n         </li>\n         <li>\n           <a href=\"file_storage.html\">\n-            <i className=\"ico file\"></i>\n-            <span className=\"links_name\">파일 보관함</span>\n+            <i class='ico file'></i>\n+            <span class=\"links_name\">파일 보관함</span>\n           </a>\n         </li>\n         <li>\n           <a href=\"form_list.html\">\n-            <i className=\"ico form\"></i>\n-            <span className=\"links_name\">상담 신청폼</span>\n+            <i class='ico form'></i>\n+            <span class=\"links_name\">상담 신청폼</span>\n           </a>\n         </li>\n-      </ul>\n-      <ul className=\"btm\">\n-        <li>\n-          <a href=\"#\">\n-            <i className=\"ico help\"></i>\n-            <span className=\"links_name\">자주 묻는 질문</span>\n-          </a>\n-        </li>\n-        <li>\n-          <a href=\"setting_company-info.html\">\n-            <i className=\"ico setting\"></i>\n-            <span className=\"links_name\">설정</span>\n-          </a>\n-        </li>\n-      </ul>\n-      <button type=\"button\" className=\"btn-lnb-close\">\n-        <span className=\"hide\">메뉴 닫기</span>\n-      </button>\n-    </div >\n+       </ul>\n+        <ul class=\"btm\">\n+          <li>\n+            <a href=\"#\">\n+              <i class='ico help'></i>\n+              <span class=\"links_name\">자주 묻는 질문</span>\n+            </a>\n+          </li>\n+          <li>\n+            <a href=\"setting_company-info.html\">\n+              <i class='ico setting'></i>\n+              <span class=\"links_name\">설정</span>\n+            </a>\n+          </li>\n+        </ul>\n+        <button type=\"button\" class=\"btn-lnb-close\"><span class=\"hide\">메뉴 닫기</span></button><!-- 2021-12-27 -->\n+    </nav>\n   );\n };\n \n export default SideBar;\n"
                },
                {
                    "date": 1641555995382,
                    "content": "Index: \n===================================================================\n--- \n+++ \n@@ -2,9 +2,9 @@\n import \"../../style/css/layout.css\";\n \n const SideBar = (props) => {\n   return (\n-    <nav class=\"sidebar\">\n+    <div class=\"sidebar\">\n       <div class=\"logo-details\">\n         <button type=\"button\" class=\"btn-side-open\"><img src=\"../resource/images/common/ico_logo-mark.png\" alt=\"오더체크\"></button>\n         <h1 class=\"logo_name\"><img src=\"../resource/images/common/ico_logo-name.png\" alt=\"오더체크\"/></h1>\n       </div>\n@@ -49,9 +49,9 @@\n             </a>\n           </li>\n         </ul>\n         <button type=\"button\" class=\"btn-lnb-close\"><span class=\"hide\">메뉴 닫기</span></button><!-- 2021-12-27 -->\n-    </nav>\n+    </div>\n   );\n };\n \n export default SideBar;\n"
                },
                {
                    "date": 1641556013235,
                    "content": "Index: \n===================================================================\n--- \n+++ \n@@ -4,9 +4,9 @@\n const SideBar = (props) => {\n   return (\n     <div class=\"sidebar\">\n       <div class=\"logo-details\">\n-        <button type=\"button\" class=\"btn-side-open\"><img src=\"../resource/images/common/ico_logo-mark.png\" alt=\"오더체크\"></button>\n+        <button type=\"button\" class=\"btn-side-open\"><img src=\"../resource/images/common/ico_logo-mark.png\" alt=\"오더체크\"/></button>\n         <h1 class=\"logo_name\"><img src=\"../resource/images/common/ico_logo-name.png\" alt=\"오더체크\"/></h1>\n       </div>\n \n       <ul class=\"nav-list\">\n"
                },
                {
                    "date": 1641556030210,
                    "content": "Index: \n===================================================================\n--- \n+++ \n@@ -4,9 +4,9 @@\n const SideBar = (props) => {\n   return (\n     <div class=\"sidebar\">\n       <div class=\"logo-details\">\n-        <button type=\"button\" class=\"btn-side-open\"><img src=\"../resource/images/common/ico_logo-mark.png\" alt=\"오더체크\"/></button>\n+        <button type=\"button\" class=\"btn-side-open\"><div src=\"../resource/images/common/ico_logo-mark.png\" alt=\"오더체크\"/></button>\n         <h1 class=\"logo_name\"><img src=\"../resource/images/common/ico_logo-name.png\" alt=\"오더체크\"/></h1>\n       </div>\n \n       <ul class=\"nav-list\">\n"
                },
                {
                    "date": 1641556038112,
                    "content": "Index: \n===================================================================\n--- \n+++ \n@@ -4,9 +4,9 @@\n const SideBar = (props) => {\n   return (\n     <div class=\"sidebar\">\n       <div class=\"logo-details\">\n-        <button type=\"button\" class=\"btn-side-open\"><div src=\"../resource/images/common/ico_logo-mark.png\" alt=\"오더체크\"/></button>\n+        <button type=\"button\" class=\"btn-side-open\"><img src=\"../resource/images/common/ico_logo-mark.png\" alt=\"오더체크\"></button>\n         <h1 class=\"logo_name\"><img src=\"../resource/images/common/ico_logo-name.png\" alt=\"오더체크\"/></h1>\n       </div>\n \n       <ul class=\"nav-list\">\n"
                },
                {
                    "date": 1641556057376,
                    "content": "Index: \n===================================================================\n--- \n+++ \n@@ -4,16 +4,26 @@\n const SideBar = (props) => {\n   return (\n     <div class=\"sidebar\">\n       <div class=\"logo-details\">\n-        <button type=\"button\" class=\"btn-side-open\"><img src=\"../resource/images/common/ico_logo-mark.png\" alt=\"오더체크\"></button>\n-        <h1 class=\"logo_name\"><img src=\"../resource/images/common/ico_logo-name.png\" alt=\"오더체크\"/></h1>\n+        <button type=\"button\" class=\"btn-side-open\">\n+          <img\n+            src=\"../resource/images/common/ico_logo-mark.png\"\n+            alt=\"오더체크\"\n+          />\n+        </button>\n+        <h1 class=\"logo_name\">\n+          <img\n+            src=\"../resource/images/common/ico_logo-name.png\"\n+            alt=\"오더체크\"\n+          />\n+        </h1>\n       </div>\n \n       <ul class=\"nav-list\">\n         <li>\n           <a href=\"dashboard.html\">\n-            <i class='ico home'></i>\n+            <i class=\"ico home\"></i>\n             <span class=\"links_name\">홈</span>\n           </a>\n         </li>\n         <li class=\"on\">\n@@ -23,34 +33,36 @@\n           </a>\n         </li>\n         <li>\n           <a href=\"file_storage.html\">\n-            <i class='ico file'></i>\n+            <i class=\"ico file\"></i>\n             <span class=\"links_name\">파일 보관함</span>\n           </a>\n         </li>\n         <li>\n           <a href=\"form_list.html\">\n-            <i class='ico form'></i>\n+            <i class=\"ico form\"></i>\n             <span class=\"links_name\">상담 신청폼</span>\n           </a>\n         </li>\n-       </ul>\n-        <ul class=\"btm\">\n-          <li>\n-            <a href=\"#\">\n-              <i class='ico help'></i>\n-              <span class=\"links_name\">자주 묻는 질문</span>\n-            </a>\n-          </li>\n-          <li>\n-            <a href=\"setting_company-info.html\">\n-              <i class='ico setting'></i>\n-              <span class=\"links_name\">설정</span>\n-            </a>\n-          </li>\n-        </ul>\n-        <button type=\"button\" class=\"btn-lnb-close\"><span class=\"hide\">메뉴 닫기</span></button><!-- 2021-12-27 -->\n+      </ul>\n+      <ul class=\"btm\">\n+        <li>\n+          <a href=\"#\">\n+            <i class=\"ico help\"></i>\n+            <span class=\"links_name\">자주 묻는 질문</span>\n+          </a>\n+        </li>\n+        <li>\n+          <a href=\"setting_company-info.html\">\n+            <i class=\"ico setting\"></i>\n+            <span class=\"links_name\">설정</span>\n+          </a>\n+        </li>\n+      </ul>\n+      <button type=\"button\" class=\"btn-lnb-close\">\n+        <span class=\"hide\">메뉴 닫기</span>\n+      </button>\n     </div>\n   );\n };\n \n"
                },
                {
                    "date": 1641556083789,
                    "content": "Index: \n===================================================================\n--- \n+++ \n@@ -6,9 +6,9 @@\n     <div class=\"sidebar\">\n       <div class=\"logo-details\">\n         <button type=\"button\" class=\"btn-side-open\">\n           <img\n-            src=\"../resource/images/common/ico_logo-mark.png\"\n+            src=\"../../resource/images/common/ico_logo-mark.png\"\n             alt=\"오더체크\"\n           />\n         </button>\n         <h1 class=\"logo_name\">\n"
                },
                {
                    "date": 1641556108524,
                    "content": "Index: \n===================================================================\n--- \n+++ \n@@ -12,9 +12,9 @@\n           />\n         </button>\n         <h1 class=\"logo_name\">\n           <img\n-            src=\"../resource/images/common/ico_logo-name.png\"\n+            src=\"../../resource/images/common/ico_logo-name.png\"\n             alt=\"오더체크\"\n           />\n         </h1>\n       </div>\n"
                },
                {
                    "date": 1641556148655,
                    "content": "Index: \n===================================================================\n--- \n+++ \n@@ -1,6 +1,6 @@\n import React from \"react\";\n-import \"../../style/css/layout.css\";\n+import \"layout.css\";\n \n const SideBar = (props) => {\n   return (\n     <div class=\"sidebar\">\n"
                },
                {
                    "date": 1641556154399,
                    "content": "Index: \n===================================================================\n--- \n+++ \n@@ -1,6 +1,6 @@\n import React from \"react\";\n-import \"layout.css\";\n+import \"../../style/css/layout.css\";\n \n const SideBar = (props) => {\n   return (\n     <div class=\"sidebar\">\n"
                },
                {
                    "date": 1641557805754,
                    "content": "Index: \n===================================================================\n--- \n+++ \n@@ -1,7 +1,11 @@\n import React from \"react\";\n-import \"../../style/css/layout.css\";\n+// import \"../../style/css/layout.css\";\n \n+import \"../../resource/css/contents.css\";\n+import \"../../resource/css/layout.css\";\n+import \"../../resource/css/contents.css\";\n+\n const SideBar = (props) => {\n   return (\n     <div class=\"sidebar\">\n       <div class=\"logo-details\">\n"
                },
                {
                    "date": 1641557816971,
                    "content": "Index: \n===================================================================\n--- \n+++ \n@@ -1,8 +1,8 @@\n import React from \"react\";\n // import \"../../style/css/layout.css\";\n \n-import \"../../resource/css/contents.css\";\n+import \"../../resource/css/vendor/nice-select.css\";\n import \"../../resource/css/layout.css\";\n import \"../../resource/css/contents.css\";\n \n const SideBar = (props) => {\n"
                },
                {
                    "date": 1641558194079,
                    "content": "Index: \n===================================================================\n--- \n+++ \n@@ -1,8 +1,8 @@\n import React from \"react\";\n // import \"../../style/css/layout.css\";\n \n-import \"../../resource/css/vendor/nice-select.css\";\n+// import \"../../resource/css/vendor/nice-select.css\";\n import \"../../resource/css/layout.css\";\n import \"../../resource/css/contents.css\";\n \n const SideBar = (props) => {\n"
                },
                {
                    "date": 1641558201082,
                    "content": "Index: \n===================================================================\n--- \n+++ \n@@ -1,8 +1,7 @@\n import React from \"react\";\n // import \"../../style/css/layout.css\";\n \n-// import \"../../resource/css/vendor/nice-select.css\";\n import \"../../resource/css/layout.css\";\n import \"../../resource/css/contents.css\";\n \n const SideBar = (props) => {\n"
                },
                {
                    "date": 1641558208461,
                    "content": "Index: \n===================================================================\n--- \n+++ \n@@ -1,9 +1,9 @@\n import React from \"react\";\n // import \"../../style/css/layout.css\";\n \n import \"../../resource/css/layout.css\";\n-import \"../../resource/css/contents.css\";\n+// import \"../../resource/css/contents.css\";\n \n const SideBar = (props) => {\n   return (\n     <div class=\"sidebar\">\n"
                },
                {
                    "date": 1641558214057,
                    "content": "Index: \n===================================================================\n--- \n+++ \n@@ -1,9 +1,8 @@\n import React from \"react\";\n // import \"../../style/css/layout.css\";\n \n import \"../../resource/css/layout.css\";\n-// import \"../../resource/css/contents.css\";\n \n const SideBar = (props) => {\n   return (\n     <div class=\"sidebar\">\n"
                },
                {
                    "date": 1641558363533,
                    "content": "Index: \n===================================================================\n--- \n+++ \n@@ -12,14 +12,8 @@\n             src=\"../../resource/images/common/ico_logo-mark.png\"\n             alt=\"오더체크\"\n           />\n         </button>\n-        <h1 class=\"logo_name\">\n-          <img\n-            src=\"../../resource/images/common/ico_logo-name.png\"\n-            alt=\"오더체크\"\n-          />\n-        </h1>\n       </div>\n \n       <ul class=\"nav-list\">\n         <li>\n"
                },
                {
                    "date": 1641558371392,
                    "content": "Index: \n===================================================================\n--- \n+++ \n@@ -6,14 +6,15 @@\n const SideBar = (props) => {\n   return (\n     <div class=\"sidebar\">\n       <div class=\"logo-details\">\n-        <button type=\"button\" class=\"btn-side-open\">\n+        <button type=\"button\" class=\"btn-side-open\"></button>\n+        <h1 class=\"logo_name\">\n           <img\n-            src=\"../../resource/images/common/ico_logo-mark.png\"\n+            src=\"../../resource/images/common/ico_logo-name.png\"\n             alt=\"오더체크\"\n           />\n-        </button>\n+        </h1>\n       </div>\n \n       <ul class=\"nav-list\">\n         <li>\n"
                },
                {
                    "date": 1641558379940,
                    "content": "Index: \n===================================================================\n--- \n+++ \n@@ -6,9 +6,8 @@\n const SideBar = (props) => {\n   return (\n     <div class=\"sidebar\">\n       <div class=\"logo-details\">\n-        <button type=\"button\" class=\"btn-side-open\"></button>\n         <h1 class=\"logo_name\">\n           <img\n             src=\"../../resource/images/common/ico_logo-name.png\"\n             alt=\"오더체크\"\n"
                },
                {
                    "date": 1641559448906,
                    "content": "Index: \n===================================================================\n--- \n+++ \n@@ -6,8 +6,11 @@\n const SideBar = (props) => {\n   return (\n     <div class=\"sidebar\">\n       <div class=\"logo-details\">\n+        <button type=\"button\" class=\"btn-side-open\">\n+          <img src=\"../../resource/images/common/ico_logo-mark.png\" />\n+        </button>\n         <h1 class=\"logo_name\">\n           <img\n             src=\"../../resource/images/common/ico_logo-name.png\"\n             alt=\"오더체크\"\n"
                },
                {
                    "date": 1641559455220,
                    "content": "Index: \n===================================================================\n--- \n+++ \n@@ -7,9 +7,12 @@\n   return (\n     <div class=\"sidebar\">\n       <div class=\"logo-details\">\n         <button type=\"button\" class=\"btn-side-open\">\n-          <img src=\"../../resource/images/common/ico_logo-mark.png\" />\n+          <img\n+            src=\"../../resource/images/common/ico_logo-mark.png\"\n+            alt=\"오더체크\"\n+          />\n         </button>\n         <h1 class=\"logo_name\">\n           <img\n             src=\"../../resource/images/common/ico_logo-name.png\"\n"
                },
                {
                    "date": 1641559540695,
                    "content": "Index: \n===================================================================\n--- \n+++ \n@@ -7,12 +7,9 @@\n   return (\n     <div class=\"sidebar\">\n       <div class=\"logo-details\">\n         <button type=\"button\" class=\"btn-side-open\">\n-          <img\n-            src=\"../../resource/images/common/ico_logo-mark.png\"\n-            alt=\"오더체크\"\n-          />\n+          <img src=\"../../resource/images/common/ico_logo-mark.png\" />\n         </button>\n         <h1 class=\"logo_name\">\n           <img\n             src=\"../../resource/images/common/ico_logo-name.png\"\n"
                },
                {
                    "date": 1641559559395,
                    "content": "Index: \n===================================================================\n--- \n+++ \n@@ -7,9 +7,12 @@\n   return (\n     <div class=\"sidebar\">\n       <div class=\"logo-details\">\n         <button type=\"button\" class=\"btn-side-open\">\n-          <img src=\"../../resource/images/common/ico_logo-mark.png\" />\n+          <img\n+            src=\"../../resource/images/common/ico_logo-mark.png\"\n+            alt=\"오더체크\"\n+          />\n         </button>\n         <h1 class=\"logo_name\">\n           <img\n             src=\"../../resource/images/common/ico_logo-name.png\"\n"
                },
                {
                    "date": 1641559596969,
                    "content": "Index: \n===================================================================\n--- \n+++ \n@@ -40,9 +40,9 @@\n             <span class=\"links_name\">파일 보관함</span>\n           </a>\n         </li>\n         <li>\n-          <a href=\"form_list.html\">\n+          {/* <a href=\"form_list.html\"> */}\n             <i class=\"ico form\"></i>\n             <span class=\"links_name\">상담 신청폼</span>\n           </a>\n         </li>\n"
                },
                {
                    "date": 1641559633911,
                    "content": "Index: \n===================================================================\n--- \n+++ \n@@ -7,12 +7,14 @@\n   return (\n     <div class=\"sidebar\">\n       <div class=\"logo-details\">\n         <button type=\"button\" class=\"btn-side-open\">\n-          <img\n-            src=\"../../resource/images/common/ico_logo-mark.png\"\n-            alt=\"오더체크\"\n-          />\n+          <div>\n+            <img\n+              src=\"../../resource/images/common/ico_logo-mark.png\"\n+              alt=\"오더체크\"\n+            />\n+          </div>\n         </button>\n         <h1 class=\"logo_name\">\n           <img\n             src=\"../../resource/images/common/ico_logo-name.png\"\n@@ -40,9 +42,9 @@\n             <span class=\"links_name\">파일 보관함</span>\n           </a>\n         </li>\n         <li>\n-          {/* <a href=\"form_list.html\"> */}\n+          <a href=\"form_list.html\">\n             <i class=\"ico form\"></i>\n             <span class=\"links_name\">상담 신청폼</span>\n           </a>\n         </li>\n"
                },
                {
                    "date": 1641559642541,
                    "content": "Index: \n===================================================================\n--- \n+++ \n@@ -7,14 +7,12 @@\n   return (\n     <div class=\"sidebar\">\n       <div class=\"logo-details\">\n         <button type=\"button\" class=\"btn-side-open\">\n-          <div>\n-            <img\n-              src=\"../../resource/images/common/ico_logo-mark.png\"\n-              alt=\"오더체크\"\n-            />\n-          </div>\n+          <img\n+            src=\"../../resource/images/common/ico_logo-mark.png\"\n+            alt=\"오더체크\"\n+          />\n         </button>\n         <h1 class=\"logo_name\">\n           <img\n             src=\"../../resource/images/common/ico_logo-name.png\"\n"
                },
                {
                    "date": 1641559651695,
                    "content": "Index: \n===================================================================\n--- \n+++ \n@@ -5,14 +5,15 @@\n \n const SideBar = (props) => {\n   return (\n     <div class=\"sidebar\">\n+      <img\n+        src=\"../../resource/images/common/ico_logo-mark.png\"\n+        alt=\"오더체크\"\n+      />\n       <div class=\"logo-details\">\n         <button type=\"button\" class=\"btn-side-open\">\n-          <img\n-            src=\"../../resource/images/common/ico_logo-mark.png\"\n-            alt=\"오더체크\"\n-          />\n+          aa\n         </button>\n         <h1 class=\"logo_name\">\n           <img\n             src=\"../../resource/images/common/ico_logo-name.png\"\n"
                },
                {
                    "date": 1641559666073,
                    "content": "Index: \n===================================================================\n--- \n+++ \n@@ -5,15 +5,14 @@\n \n const SideBar = (props) => {\n   return (\n     <div class=\"sidebar\">\n-      <img\n-        src=\"../../resource/images/common/ico_logo-mark.png\"\n-        alt=\"오더체크\"\n-      />\n       <div class=\"logo-details\">\n         <button type=\"button\" class=\"btn-side-open\">\n-          aa\n+          <img\n+            src=\"../../resource/images/common/bg_calendar-start.png\"\n+            alt=\"오더체크\"\n+          />\n         </button>\n         <h1 class=\"logo_name\">\n           <img\n             src=\"../../resource/images/common/ico_logo-name.png\"\n"
                },
                {
                    "date": 1641559673607,
                    "content": "Index: \n===================================================================\n--- \n+++ \n@@ -8,9 +8,9 @@\n     <div class=\"sidebar\">\n       <div class=\"logo-details\">\n         <button type=\"button\" class=\"btn-side-open\">\n           <img\n-            src=\"../../resource/images/common/bg_calendar-start.png\"\n+            src=\"../../resource/images/common/ico_btn-template.png\"\n             alt=\"오더체크\"\n           />\n         </button>\n         <h1 class=\"logo_name\">\n"
                },
                {
                    "date": 1641559681130,
                    "content": "Index: \n===================================================================\n--- \n+++ \n@@ -6,14 +6,12 @@\n const SideBar = (props) => {\n   return (\n     <div class=\"sidebar\">\n       <div class=\"logo-details\">\n-        <button type=\"button\" class=\"btn-side-open\">\n-          <img\n-            src=\"../../resource/images/common/ico_btn-template.png\"\n-            alt=\"오더체크\"\n-          />\n-        </button>\n+        <img\n+          src=\"../../resource/images/common/ico_btn-template.png\"\n+          alt=\"오더체크\"\n+        />\n         <h1 class=\"logo_name\">\n           <img\n             src=\"../../resource/images/common/ico_logo-name.png\"\n             alt=\"오더체크\"\n"
                },
                {
                    "date": 1641560342692,
                    "content": "Index: \n===================================================================\n--- \n+++ \n@@ -6,12 +6,14 @@\n const SideBar = (props) => {\n   return (\n     <div class=\"sidebar\">\n       <div class=\"logo-details\">\n-        <img\n-          src=\"../../resource/images/common/ico_btn-template.png\"\n-          alt=\"오더체크\"\n-        />\n+        <button type=\"button\" class=\"btn-side-open\">\n+          <img\n+            src=\"../../resource/images/common/ico_btn-template.png\"\n+            alt=\"오더체크\"\n+          />\n+        </button>\n         <h1 class=\"logo_name\">\n           <img\n             src=\"../../resource/images/common/ico_logo-name.png\"\n             alt=\"오더체크\"\n"
                }
            ],
            "date": 1641554524665,
            "name": "Commit-0",
            "content": ""
        }
    ]
}